aws_ssooidc/__init__.py
aws_ssooidc/__main__.py
aws_ssooidc-2024.1.0.0.dist-info/METADATA
aws_ssooidc-2024.1.0.0.dist-info/WHEEL
aws_ssooidc-2024.1.0.0.dist-info/RECORD
